flaskel/__init__.py
flaskel/builder.py
flaskel/config.py
flaskel/converters.py
flaskel/flaskel.py
flaskel/middlewares.py
flaskel/standalone.py
flaskel/version.py
flaskel/ext/__init__.py
flaskel/ext/auth.py
flaskel/ext/caching.py
flaskel/ext/datetime.py
flaskel/ext/default.py
flaskel/ext/ipban.py
flaskel/ext/jobs.py
flaskel/ext/limit.py
flaskel/ext/mongo.py
flaskel/ext/redis.py
flaskel/ext/sendmail.py
flaskel/ext/useragent.py
flaskel/ext/cloudflare/__init__.py
flaskel/ext/cloudflare/remote.py
flaskel/ext/crypto/__init__.py
flaskel/ext/crypto/argon.py
flaskel/ext/errors/__init__.py
flaskel/ext/errors/dispatchers.py
flaskel/ext/errors/exception.py
flaskel/ext/errors/handler.py
flaskel/ext/errors/normalize.py
flaskel/ext/healthcheck/__init__.py
flaskel/ext/healthcheck/checkers.py
flaskel/ext/healthcheck/health.py
flaskel/ext/logging/__init__.py
flaskel/ext/logging/filters.py
flaskel/ext/logging/formatters.py
flaskel/ext/logging/handlers.py
flaskel/ext/logging/logging.py
flaskel/ext/logging/builders/__init__.py
flaskel/ext/logging/builders/base.py
flaskel/ext/logging/builders/json.py
flaskel/ext/logging/builders/text.py
flaskel/ext/response/__init__.py
flaskel/ext/response/builder.py
flaskel/ext/response/config.py
flaskel/ext/response/dictutils.py
flaskel/ext/response/builders/__init__.py
flaskel/ext/response/builders/base64.py
flaskel/ext/response/builders/builder.py
flaskel/ext/response/builders/csv.py
flaskel/ext/response/builders/html.py
flaskel/ext/response/builders/json.py
flaskel/ext/response/builders/xml.py
flaskel/ext/response/builders/yaml.py
flaskel/ext/sqlalchemy/__init__.py
flaskel/ext/sqlalchemy/model.py
flaskel/ext/templating/__init__.py
flaskel/ext/templating/default.py
flaskel/ext/templating/filters.py
flaskel/ext/templating/functions.py
flaskel/ext/templating/support.py
flaskel/ext/websocket/__init__.py
flaskel/extra/__init__.py
flaskel/extra/account.py
flaskel/extra/mobile_support.py
flaskel/extra/notification.py
flaskel/extra/apidoc/__init__.py
Flaskel-3.1.0.dist-info/METADATA
Flaskel-3.1.0.dist-info/WHEEL
Flaskel-3.1.0.dist-info/entry_points.txt
Flaskel-3.1.0.dist-info/top_level.txt
Flaskel-3.1.0.dist-info/RECORD
