Metadata-Version: 2.1
Name: Flaskel
Version: 3.1.0
Summary: Skeleton for flask applications
Home-page: https://github.com/cs91chris/flaskel
Author: cs91chris
Author-email: cs91chris@voidbrain.me
License: MIT
Platform: any
Classifier: Environment :: Web Environment
Classifier: Framework :: Flask
Classifier: Intended Audience :: Developers
Classifier: License :: OSI Approved :: MIT License
Classifier: Operating System :: OS Independent
Classifier: Programming Language :: Python :: 3.6
Classifier: Topic :: Software Development
Classifier: Topic :: Internet :: WWW/HTTP :: Dynamic Content
Classifier: Topic :: Internet :: WWW/HTTP :: HTTP Servers
Classifier: Topic :: Internet :: WWW/HTTP :: WSGI :: Application
Requires-Python: >3.6
Requires-Dist: Flask <2.3
Requires-Dist: Flask-Caching
Requires-Dist: Flask-Cors
Requires-Dist: Flask-HTTPAuth
Requires-Dist: Flask-JWT-Extended
Requires-Dist: Flask-Limiter
Requires-Dist: Flask-SQLAlchemy
Requires-Dist: json2html
Requires-Dist: jsonschema
Requires-Dist: nest-asyncio
Requires-Dist: netaddr
Requires-Dist: vbcore[all] ==2.0.*
Requires-Dist: webargs
Requires-Dist: xmltodict
Provides-Extra: all
Requires-Dist: pyfcm <2 ; extra == 'all'
Requires-Dist: stripe ; extra == 'all'
Requires-Dist: redis ; extra == 'all'
Requires-Dist: hiredis ; extra == 'all'
Requires-Dist: gunicorn ; extra == 'all'
Requires-Dist: gevent ; extra == 'all'
Requires-Dist: gevent-websocket ; extra == 'all'
Requires-Dist: Flask-Mail ; extra == 'all'
Requires-Dist: Flask-APScheduler ; extra == 'all'
Requires-Dist: flask-pymongo ; extra == 'all'
Requires-Dist: flask-socketio ; extra == 'all'
Provides-Extra: test
Requires-Dist: coverage ; extra == 'test'
Requires-Dist: pytest ; extra == 'test'
Requires-Dist: pytest-cov ; extra == 'test'
Requires-Dist: responses ; extra == 'test'
